keywordsai_eval/__init__.py
keywordsai_eval/backends/base/__init__.py
keywordsai_eval/backends/base/main.py
keywordsai_eval/backends/redis_stack/__init__.py
keywordsai_eval/backends/redis_stack/category_prompts.json
keywordsai_eval/backends/redis_stack/main.py
keywordsai_eval/backends/redis_stack/redis_ops.py
keywordsai_eval/backends/redis_stack/topic_prompts.json
keywordsai_eval/main.py
keywordsai_eval/settings.py
keywordsai_eval/utils.py
keywordsai_eval-0.1.9.dist-info/METADATA
keywordsai_eval-0.1.9.dist-info/WHEEL
keywordsai_eval-0.1.9.dist-info/RECORD
